README.rst
setup.py
./temperatures.py
temperatures.egg-info/PKG-INFO
temperatures.egg-info/SOURCES.txt
temperatures.egg-info/dependency_links.txt
temperatures.egg-info/entry_points.txt
temperatures.egg-info/top_level.txt