Metadata-Version: 1.1
Name: temperatures
Version: 0.0.1
Summary: A program that shows system temperatures in a concise string.
Home-page: https://github.com/luismsgomes/temperatures
Author: Luís Gomes
Author-email: luismsgomes@gmail.com
License: MIT
Keywords: convenience system monitor
Platform: UNKNOWN
Classifier: Development Status :: 3 - Alpha
Classifier: License :: OSI Approved :: MIT License
Classifier: Programming Language :: Python :: 3.7
